llama_cpp_agent/__init__.py
llama_cpp_agent/chain.py
llama_cpp_agent/function_calling.py
llama_cpp_agent/function_calling_agent.py
llama_cpp_agent/hermes_2_pro_agent.py
llama_cpp_agent/llm_agent.py
llama_cpp_agent/llm_prompt_template.py
llama_cpp_agent/messages_formatter.py
llama_cpp_agent/mixtral_8x22b_agent.py
llama_cpp_agent/mixture_of_agents.py
llama_cpp_agent/output_parser.py
llama_cpp_agent/prompt_templates.py
llama_cpp_agent/prompts.py
llama_cpp_agent/structured_output_agent.py
llama_cpp_agent/text_utils.py
llama_cpp_agent/agent_memory/__init__.py
llama_cpp_agent/agent_memory/core_memory_manager.py
llama_cpp_agent/agent_memory/event_memory.py
llama_cpp_agent/agent_memory/event_memory_manager.py
llama_cpp_agent/agent_memory/memory_tools.py
llama_cpp_agent/agent_memory/retrieval_memory.py
llama_cpp_agent/agent_memory/retrieval_memory_manager.py
llama_cpp_agent/chat_history/__init__.py
llama_cpp_agent/chat_history/basic_chat_history.py
llama_cpp_agent/chat_history/chat_history_base.py
llama_cpp_agent/chat_history/messages.py
llama_cpp_agent/gbnf_grammar_generator/__init__.py
llama_cpp_agent/gbnf_grammar_generator/gbnf_grammar_from_pydantic_models.py
llama_cpp_agent/json_schema_generator/__init__.py
llama_cpp_agent/json_schema_generator/schema_generator.py
llama_cpp_agent/llm_documentation/__init__.py
llama_cpp_agent/llm_documentation/documentation_generation.py
llama_cpp_agent/llm_output_settings/__init__.py
llama_cpp_agent/llm_output_settings/settings.py
llama_cpp_agent/providers/__init__.py
llama_cpp_agent/providers/groq.py
llama_cpp_agent/providers/llama_cpp_python.py
llama_cpp_agent/providers/llama_cpp_server.py
llama_cpp_agent/providers/provider_base.py
llama_cpp_agent/providers/tgi_server.py
llama_cpp_agent/providers/vllm_server.py
llama_cpp_agent/rag/__init__.py
llama_cpp_agent/rag/rag_colbert_reranker.py
llama_cpp_agent/tools/__init__.py
llama_cpp_agent/tools/summarizing/__init__.py
llama_cpp_agent/tools/summarizing/tool.py
llama_cpp_agent-0.2.35.dist-info/LICENSE
llama_cpp_agent-0.2.35.dist-info/METADATA
llama_cpp_agent-0.2.35.dist-info/WHEEL
llama_cpp_agent-0.2.35.dist-info/top_level.txt
llama_cpp_agent-0.2.35.dist-info/RECORD
