Metadata-Version: 2.1
Name: llama-cpp-agent
Version: 0.2.35
Summary: A framework for building LLM based AI agents with llama.cpp.
Author-email: Maximilian Winter <maximilian.winter.91@gmail.com>
Project-URL: Homepage, https://github.com/Maximilian-Winter/llama-cpp-agent
Project-URL: Bug Tracker, https://github.com/Maximilian-Winter/llama-cpp-agent/issues
Classifier: Programming Language :: Python :: 3
Classifier: License :: OSI Approved :: MIT License
Classifier: Operating System :: OS Independent
Requires-Python: >=3.10
License-File: LICENSE
Requires-Dist: llama-cpp-python>=0.2.60
Requires-Dist: pydantic>=2.5.3
Requires-Dist: requests>=2.31.0
Requires-Dist: docstring_parser
Requires-Dist: aiohttp
Provides-Extra: agent-memory
Requires-Dist: chromadb; extra == "agent-memory"
Requires-Dist: SQLAlchemy; extra == "agent-memory"
Requires-Dist: numpy; extra == "agent-memory"
Requires-Dist: scipy; extra == "agent-memory"
Provides-Extra: rag
Requires-Dist: ragatouille; extra == "rag"
Provides-Extra: vllm-provider
Requires-Dist: openai; extra == "vllm-provider"
Requires-Dist: transformers; extra == "vllm-provider"
Requires-Dist: sentencepiece; extra == "vllm-provider"
Requires-Dist: protobuf; extra == "vllm-provider"
Provides-Extra: groq-provider
Requires-Dist: groq; extra == "groq-provider"
Provides-Extra: mixtral-agent
Requires-Dist: mistral-common; extra == "mixtral-agent"
Provides-Extra: web-search-summarization
Requires-Dist: duckduckgo_search; extra == "web-search-summarization"
Requires-Dist: trafilatura; extra == "web-search-summarization"
Requires-Dist: lxml-html-clean; extra == "web-search-summarization"
Requires-Dist: lxml; extra == "web-search-summarization"
Requires-Dist: googlesearch-python; extra == "web-search-summarization"
Requires-Dist: beautifulsoup4; extra == "web-search-summarization"
Requires-Dist: readability-lxml; extra == "web-search-summarization"
